<eww>
  <definitions>
    <!-- This is the place where you structure your widgets, align them and stuff. -->

    <def name="noneBar">
      <box class="noneBar" orientation="h">
      </box>
    </def>

  </definitions>

  <variables>
  </variables>

  <windows>
    <!-- These are the windows -->
    <window name="noneBar" screen="0" stacking="bg">
      <geometry x="0%" y="0%" width="100%" height="32px"/>
      <reserve side="top" distance="32px"/>
      <widget>
        <noneBar/>
      </widget>
    </window>
  </windows>
</eww>
